punica/__init__.py
punica/box/__init__.py
punica/box/repo_box.py
punica/cli/__init__.py
punica/cli/box_cmd.py
punica/cli/compile_cmd.py
punica/cli/decode_cmd.py
punica/cli/deploy_cmd.py
punica/cli/info_cmd.py
punica/cli/invoke_cmd.py
punica/cli/main.py
punica/cli/smartx_cmd.py
punica/cli/solo_cmd.py
punica/compile/__init__.py
punica/compile/py_contract.py
punica/config/__init__.py
punica/config/punica_config.py
punica/core/__init__.py
punica/core/base_project.py
punica/core/contract_func.py
punica/core/contract_project.py
punica/core/project_with_config.py
punica/deploy/__init__.py
punica/deploy/deploy_contract.py
punica/exception/__init__.py
punica/exception/punica_exception.py
punica/info/__init__.py
punica/info/chain_info.py
punica/invoke/__init__.py
punica/invoke/invoke_contract.py
punica/utils/__init__.py
punica/utils/file_system.py
punica/utils/output.py
punica-0.2.1.dist-info/LICENSE
punica-0.2.1.dist-info/METADATA
punica-0.2.1.dist-info/WHEEL
punica-0.2.1.dist-info/entry_points.txt
punica-0.2.1.dist-info/top_level.txt
punica-0.2.1.dist-info/RECORD
