Metadata-Version: 2.1
Name: punica
Version: 0.2.1
Summary: Ontology DApp Development Framework
Home-page: https://github.com/punicasuite/punica-python
Author: NashMiao
Author-email: wdx7266@outlook.com
Maintainer: NashMiao
Maintainer-email: wdx7266@outlook.com
License: MIT
Platform: UNKNOWN
Classifier: Development Status :: 4 - Beta
Classifier: Intended Audience :: Developers
Classifier: License :: OSI Approved :: MIT License
Classifier: Natural Language :: English
Classifier: Programming Language :: Python :: 3.6
Classifier: Programming Language :: Python :: 3.7
Classifier: Programming Language :: Python :: 3.8
Requires-Python: >=3.6,<4
Requires-Dist: halo (==0.0.26)
Requires-Dist: crayons (==0.2.0)
Requires-Dist: Click (==7.0)
Requires-Dist: requests (==2.22.0)
Requires-Dist: GitPython (==2.1.11)
Requires-Dist: ontology-python-sdk (==2.0.6)
